Metadata-Version: 2.1
Name: snakevir
Version: 2.1.0
Summary: This is a worflow that analyses some metagenomics data
Author-email: "Florian CHARRIAT (CIRAD) & Antoni Exbrayat (CIRAD)" <florian.charriat@cirad.fr>
Project-URL: Homepage, https://github.com/FlorianCHA/snakevir
Requires-Dist: click
Requires-Dist: rich-click
Requires-Dist: cookiecutter
Requires-Dist: snakemake
Requires-Dist: sphinx-copybutton
Requires-Dist: sphinx-rtd-theme
Requires-Dist: sphinx-click
